{
  "id": "1197",
  "name": "Steep Ruins",
  "attributeBlocks": {
    "this": {
      "tile_type": "R",
      "tile": "",
      "super_realm": "",
      "print": "",
      "image": "superrealm_ruins_steep",
      "facing": "light",
      "code": "SR",
      "folder": "sr_tiles_legendary",
      "stile": ""
    },
    "normal": {
      "offroad_xy": "67.9,91.8",
      "clearing_1_type": "normal",
      "clearing_1_xy": "64.9,18.6",
      "clearing_2_type": "water",
      "clearing_2_xy": "34.8,79.4",
      "clearing_3_type": "normal",
      "clearing_3_xy": "34.4,15.3",
      "clearing_4_type": "normal",
      "clearing_4_xy": "19.7,45.9",
      "clearing_5_type": "water",
      "clearing_5_xy": "81.8,52.2",
      "clearing_6_type": "mountain",
      "clearing_6_xy": "51.2,50.8",
      "path_1_from": "clearing_1",
      "path_1_to": "clearing_3",
      "path_1_type": "normal",
      "path_1_arc": "50.0,13.5",
      "path_2_from": "clearing_1",
      "path_2_to": "clearing_5",
      "path_2_type": "normal",
      "path_2_arc": "63.3,48.7",
      "path_3_from": "clearing_1",
      "path_3_to": "clearing_6",
      "path_3_type": "hidden",
      "path_3_arc": "56.0,26.5",
      "path_4_from": "clearing_2",
      "path_4_to": "SW",
      "path_4_type": "river",
      "path_4_arc": "22.9,65.7",
      "path_5_from": "clearing_2",
      "path_5_to": "clearing_5",
      "path_5_type": "river",
      "path_5_arc": "76.8,84.8",
      "path_6_from": "clearing_3",
      "path_6_to": "clearing_4",
      "path_6_type": "normal",
      "path_6_arc": "24.1,28.2",
      "path_7_from": "clearing_4",
      "path_7_to": "clearing_6",
      "path_7_type": "normal",
      "path_8_from": "clearing_2",
      "path_8_to": "clearing_6",
      "path_8_type": "normal",
      "path_8_arc": "45.9,65.9",
      "path_9_from": "clearing_5",
      "path_9_to": "NE",
      "path_9_type": "river",
      "path_9_arc": "76.4,30.5"
    },
    "enchanted": {
      "offroad_xy": "69.5,90.6",
      "clearing_1_type": "normal",
      "clearing_1_xy": "64.5,17.7",
      "clearing_1_magic": "R",
      "clearing_2_type": "water",
      "clearing_2_xy": "35.0,79.0",
      "clearing_2_magic": "R",
      "clearing_3_type": "normal",
      "clearing_3_xy": "34.2,14.6",
      "clearing_3_magic": "R",
      "clearing_4_type": "normal",
      "clearing_4_xy": "19.3,45.4",
      "clearing_4_magic": "R",
      "clearing_5_type": "water",
      "clearing_5_xy": "81.4,51.7",
      "clearing_5_magic": "R",
      "clearing_6_type": "mountain",
      "clearing_6_xy": "51.0,50.8",
      "clearing_6_magic": "R",
      "path_1_from": "clearing_1",
      "path_1_to": "clearing_3",
      "path_1_type": "normal",
      "path_1_arc": "46.9,10.4",
      "path_2_from": "clearing_1",
      "path_2_to": "clearing_6",
      "path_2_type": "normal",
      "path_2_arc": "57.8,31.4",
      "path_3_from": "clearing_2",
      "path_3_to": "SW",
      "path_3_type": "river",
      "path_3_arc": "20.9,64.8",
      "path_4_from": "clearing_2",
      "path_4_to": "clearing_4",
      "path_4_type": "normal",
      "path_4_arc": "32.8,60.3",
      "path_5_from": "clearing_2",
      "path_5_to": "clearing_5",
      "path_5_type": "river",
      "path_5_arc": "76.8,84.8",
      "path_6_from": "clearing_3",
      "path_6_to": "clearing_4",
      "path_6_type": "hidden",
      "path_6_arc": "26.6,27.2",
      "path_7_from": "clearing_4",
      "path_7_to": "clearing_6",
      "path_7_type": "hidden",
      "path_8_from": "clearing_5",
      "path_8_to": "NE",
      "path_8_type": "river",
      "path_8_arc": "74.1,29.3",
      "path_9_from": "clearing_5",
      "path_9_to": "clearing_6",
      "path_9_type": "hidden"
    }
  },
  "parts": []
}